{
  "info": {
    "name": "Student Management API",
    "description": "RESTful API for managing student records with authentication and file uploads",
    "version": "1.0.0",
    "schema": "https://schema.getpostman.com/json/collection/v2.1.0/collection.json"
  },
  "item": [
    {
      "name": "Authentication",
      "item": [
        {
          "name": "Register User",
          "request": {
            "method": "POST",
            "header": [
              {
                "key": "Content-Type",
                "value": "application/json",
                "type": "text"
              }
            ],
            "body": {
              "mode": "raw",
              "raw": "{\n  \"name\": \"John Doe\",\n  \"email\": \"john@example.com\",\n  \"password\": \"securePassword123\"\n}"
            },
            "url": {
              "raw": "http://localhost:5000/api/auth/register",
              "protocol": "http",
              "host": ["localhost"],
              "port": "5000",
              "path": ["api", "auth", "register"]
            }
          }
        },
        {
          "name": "Login User",
          "request": {
            "method": "POST",
            "header": [
              {
                "key": "Content-Type",
                "value": "application/json",
                "type": "text"
              }
            ],
            "body": {
              "mode": "raw",
              "raw": "{\n  \"email\": \"john@example.com\",\n  \"password\": \"securePassword123\"\n}"
            },
            "url": {
              "raw": "http://localhost:5000/api/auth/login",
              "protocol": "http",
              "host": ["localhost"],
              "port": "5000",
              "path": ["api", "auth", "login"]
            }
          }
        },
        {
          "name": "Get Profile",
          "request": {
            "method": "GET",
            "header": [
              {
                "key": "Authorization",
                "value": "Bearer {{token}}",
                "type": "text"
              }
            ],
            "url": {
              "raw": "http://localhost:5000/api/auth/profile",
              "protocol": "http",
              "host": ["localhost"],
              "port": "5000",
              "path": ["api", "auth", "profile"]
            }
          }
        },
        {
          "name": "Delete User",
          "request": {
            "method": "DELETE",
            "header": [
              {
                "key": "Authorization",
                "value": "Bearer {{token}}",
                "type": "text"
              }
            ],
            "url": {
              "raw": "http://localhost:5000/api/auth/:id",
              "protocol": "http",
              "host": ["localhost"],
              "port": "5000",
              "path": ["api", "auth", ":id"],
              "variable": [
                {
                  "key": "id",
                  "value": ""
                }
              ]
            }
          }
        }
      ]
    },
    {
      "name": "Students",
      "item": [
        {
          "name": "Get All Students",
          "request": {
            "method": "GET",
            "header": [
              {
                "key": "Authorization",
                "value": "Bearer {{token}}",
                "type": "text"
              }
            ],
            "url": {
              "raw": "http://localhost:5000/api/students",
              "protocol": "http",
              "host": ["localhost"],
              "port": "5000",
              "path": ["api", "students"]
            }
          }
        },
        {
          "name": "Get Student by ID",
          "request": {
            "method": "GET",
            "header": [
              {
                "key": "Authorization",
                "value": "Bearer {{token}}",
                "type": "text"
              }
            ],
            "url": {
              "raw": "http://localhost:5000/api/students/:id",
              "protocol": "http",
              "host": ["localhost"],
              "port": "5000",
              "path": ["api", "students", ":id"],
              "variable": [
                {
                  "key": "id",
                  "value": ""
                }
              ]
            }
          }
        },
        {
          "name": "Search Students by Name",
          "request": {
            "method": "GET",
            "header": [
              {
                "key": "Authorization",
                "value": "Bearer {{token}}",
                "type": "text"
              }
            ],
            "url": {
              "raw": "http://localhost:5000/api/students/search?name=Alice",
              "protocol": "http",
              "host": ["localhost"],
              "port": "5000",
              "path": ["api", "students", "search"],
              "query": [
                {
                  "key": "name",
                  "value": "Alice"
                }
              ]
            }
          }
        },
        {
          "name": "Create Student",
          "request": {
            "method": "POST",
            "header": [
              {
                "key": "Authorization",
                "value": "Bearer {{token}}",
                "type": "text"
              },
              {
                "key": "Content-Type",
                "value": "application/json",
                "type": "text"
              }
            ],
            "body": {
              "mode": "raw",
              "raw": "{\n  \"name\": \"Alice Johnson\",\n  \"email\": \"alice@example.com\",\n  \"rollNumber\": \"STU001\",\n  \"courseEnrolled\": \"Computer Science\",\n  \"gpa\": 3.8,\n  \"phoneNumber\": \"+1234567890\",\n  \"address\": \"123 Main St\"\n}"
            },
            "url": {
              "raw": "http://localhost:5000/api/students",
              "protocol": "http",
              "host": ["localhost"],
              "port": "5000",
              "path": ["api", "students"]
            }
          }
        },
        {
          "name": "Update Student",
          "request": {
            "method": "PUT",
            "header": [
              {
                "key": "Authorization",
                "value": "Bearer {{token}}",
                "type": "text"
              },
              {
                "key": "Content-Type",
                "value": "application/json",
                "type": "text"
              }
            ],
            "body": {
              "mode": "raw",
              "raw": "{\n  \"gpa\": 3.9,\n  \"status\": \"active\"\n}"
            },
            "url": {
              "raw": "http://localhost:5000/api/students/:id",
              "protocol": "http",
              "host": ["localhost"],
              "port": "5000",
              "path": ["api", "students", ":id"],
              "variable": [
                {
                  "key": "id",
                  "value": ""
                }
              ]
            }
          }
        },
        {
          "name": "Update Student Status",
          "request": {
            "method": "PATCH",
            "header": [
              {
                "key": "Authorization",
                "value": "Bearer {{token}}",
                "type": "text"
              },
              {
                "key": "Content-Type",
                "value": "application/json",
                "type": "text"
              }
            ],
            "body": {
              "mode": "raw",
              "raw": "{\n  \"status\": \"active\"\n}"
            },
            "url": {
              "raw": "http://localhost:5000/api/students/:id/status",
              "protocol": "http",
              "host": ["localhost"],
              "port": "5000",
              "path": ["api", "students", ":id", "status"],
              "variable": [
                {
                  "key": "id",
                  "value": ""
                }
              ]
            }
          }
        },
        {
          "name": "Upload Student Document",
          "request": {
            "method": "POST",
            "header": [
              {
                "key": "Authorization",
                "value": "Bearer {{token}}",
                "type": "text"
              }
            ],
            "body": {
              "mode": "formdata",
              "formdata": [
                {
                  "key": "document",
                  "type": "file",
                  "src": ""
                }
              ]
            },
            "url": {
              "raw": "http://localhost:5000/api/students/:id/upload",
              "protocol": "http",
              "host": ["localhost"],
              "port": "5000",
              "path": ["api", "students", ":id", "upload"],
              "variable": [
                {
                  "key": "id",
                  "value": ""
                }
              ]
            }
          }
        },
        {
          "name": "Delete Student",
          "request": {
            "method": "DELETE",
            "header": [
              {
                "key": "Authorization",
                "value": "Bearer {{token}}",
                "type": "text"
              }
            ],
            "url": {
              "raw": "http://localhost:5000/api/students/:id",
              "protocol": "http",
              "host": ["localhost"],
              "port": "5000",
              "path": ["api", "students", ":id"],
              "variable": [
                {
                  "key": "id",
                  "value": ""
                }
              ]
            }
          }
        },
        {
          "name": "Delete All Students",
          "request": {
            "method": "DELETE",
            "header": [
              {
                "key": "Authorization",
                "value": "Bearer {{token}}",
                "type": "text"
              }
            ],
            "url": {
              "raw": "http://localhost:5000/api/students",
              "protocol": "http",
              "host": ["localhost"],
              "port": "5000",
              "path": ["api", "students"]
            }
          }
        }
      ]
    }
  ],
  "variable": [
    {
      "key": "token",
      "value": "",
      "type": "string"
    }
  ]
}
